MANIFEST.in
RELEASE-VERSION
setup.py
version.py
opencv_helpers/__init__.py
opencv_helpers/analyze_recorder_log.py
opencv_helpers/camera_capture.py
opencv_helpers/codec.py
opencv_helpers/convert.py
opencv_helpers/frame_grabber.py
opencv_helpers/frame_rate.py
opencv_helpers/overlay_registration.py
opencv_helpers/pixbuf.py
opencv_helpers/recorder.py
opencv_helpers/recorder_test.py
opencv_helpers/registration_demo.py
opencv_helpers/registration_dialog.py
opencv_helpers/safe_cv.py
opencv_helpers/silence.py
opencv_helpers/sub_rect.py
opencv_helpers/test_frame_grabber.py
opencv_helpers/test_recorder.py
opencv_helpers/video.py
opencv_helpers.egg-info/PKG-INFO
opencv_helpers.egg-info/SOURCES.txt
opencv_helpers.egg-info/dependency_links.txt
opencv_helpers.egg-info/top_level.txt
opencv_helpers/cvwin/__init__.py
opencv_helpers/cvwin/cv.py
opencv_helpers/cvwin/cv2.pyd
opencv_helpers/cvwin/libopencv_calib3d231.dll
opencv_helpers/cvwin/libopencv_contrib231.dll
opencv_helpers/cvwin/libopencv_core231.dll
opencv_helpers/cvwin/libopencv_features2d231.dll
opencv_helpers/cvwin/libopencv_flann231.dll
opencv_helpers/cvwin/libopencv_gpu231.dll
opencv_helpers/cvwin/libopencv_highgui231.dll
opencv_helpers/cvwin/libopencv_imgproc231.dll
opencv_helpers/cvwin/libopencv_legacy231.dll
opencv_helpers/cvwin/libopencv_ml231.dll
opencv_helpers/cvwin/libopencv_objdetect231.dll
opencv_helpers/cvwin/libopencv_video231.dll
opencv_helpers/glade/frame_grabber.glade
opencv_helpers/glade/registration_demo.glade
opencv_helpers/statepy/__init__.py
opencv_helpers/statepy/core.py
opencv_helpers/statepy/state.py
opencv_helpers/statepy/task.py
opencv_helpers/statepy/test/__init__.py
opencv_helpers/statepy/test/main.py
opencv_helpers/statepy/test/state.py
opencv_helpers/statepy/test/task.py