Metadata-Version: 1.0
Name: opencv-helpers
Version: 1.1
Summary: Helper functions for opencv
Home-page: https://github.com/cfobel/python___opencv_examples
Author: Christian Fobel
Author-email: christian@fobel.net
License: GPLv2 License
Platform: UNKNOWN
